reposnap/__init__.py
reposnap/controllers/__init__.py
reposnap/controllers/project_controller.py
reposnap/core/__init__.py
reposnap/core/content_search.py
reposnap/core/file_system.py
reposnap/core/git_repo.py
reposnap/core/markdown_generator.py
reposnap/interfaces/__init__.py
reposnap/interfaces/cli.py
reposnap/interfaces/gui.py
reposnap/models/__init__.py
reposnap/models/file_tree.py
reposnap/utils/__init__.py
reposnap/utils/path_utils.py
reposnap-0.8.0.dist-info/METADATA
reposnap-0.8.0.dist-info/WHEEL
reposnap-0.8.0.dist-info/entry_points.txt
reposnap-0.8.0.dist-info/licenses/LICENSE
reposnap-0.8.0.dist-info/RECORD
