Metadata-Version: 2.4
Name: reposnap
Version: 0.8.0
Summary: Generate a Markdown file with all contents of your project
Author: agoloborodko
License-File: LICENSE
Requires-Python: >=3.8
Requires-Dist: gitpython>=3.1.43
Requires-Dist: pathlib>=1.0.1
Requires-Dist: pathspec>=0.12.1
Requires-Dist: urwid>=2.6.15
